{
  "sport": "Boxing",
  "heatmap": {
    "M": {
      "age": {
        "year": [
          1904,
          1908,
          1920,
          1924,
          1928,
          1932,
          1936,
          1948,
          1952,
          1956,
          1960,
          1964,
          1968,
          1972,
          1976,
          1980,
          1984,
          1988,
          1992,
          1996,
          2000,
          2004,
          2008,
          2012,
          2016
        ],
        "corr": [
          -0.331,
          -0.145,
          -0.061,
          0.108,
          -0.084,
          -0.083,
          0.047,
          -0.062,
          0.034,
          0.032,
          -0.05,
          0.072,
          0.094,
          0.014,
          -0.046,
          -0.065,
          -0.099,
          -0.007,
          -0.05,
          0.012,
          0.006,
          0.028,
          0.071,
          0.111,
          -0.085
        ]
      },
      "height": {
        "year": [
          1908,
          1920,
          1924,
          1928,
          1932,
          1936,
          1952,
          1956,
          1960,
          1964,
          1968,
          1972,
          1976,
          1980,
          1984,
          1988,
          1992,
          1996,
          2000,
          2004,
          2008,
          2012,
          2016
        ],
        "corr": [
          0.96,
          -0.262,
          0.027,
          0.047,
          0.043,
          -0.049,
          0.175,
          -0.041,
          0.089,
          0.024,
          0.118,
          0.085,
          0.112,
          0.077,
          0.162,
          0.146,
          0.006,
          0.028,
          0.044,
          0.042,
          0.083,
          0.081,
          0.093
        ]
      },
      "weight": {
        "year": [
          1904,
          1920,
          1924,
          1928,
          1932,
          1936,
          1952,
          1956,
          1960,
          1964,
          1968,
          1972,
          1976,
          1980,
          1984,
          1988,
          1992,
          1996,
          2000,
          2004,
          2008,
          2012,
          2016
        ],
        "corr": [
          0.062,
          -0.609,
          0.042,
          -0.352,
          -0.739,
          -0.315,
          0.1,
          -0.027,
          0.082,
          0.12,
          0.088,
          0.083,
          0.047,
          0.063,
          0.107,
          0.096,
          0.07,
          0.043,
          0.09,
          0.066,
          0.078,
          0.031,
          0.082
        ]
      }
    },
    "F": {
      "age": {
        "year": [
          2012,
          2016
        ],
        "corr": [
          -0.258,
          0.064
        ]
      },
      "height": {
        "year": [
          2012,
          2016
        ],
        "corr": [
          -0.214,
          0.059
        ]
      },
      "weight": {
        "year": [
          2012,
          2016
        ],
        "corr": [
          -0.072,
          -0.004
        ]
      }
    }
  },
  "bar": {
    "M": {
      "age": {
        "year": [
          1904,
          1904,
          1904,
          1904,
          1908,
          1908,
          1908,
          1908,
          1920,
          1920,
          1920,
          1920,
          1924,
          1924,
          1924,
          1924,
          1928,
          1928,
          1928,
          1928,
          1932,
          1932,
          1932,
          1932,
          1936,
          1936,
          1936,
          1936,
          1948,
          1948,
          1948,
          1948,
          1952,
          1952,
          1952,
          1952,
          1956,
          1956,
          1956,
          1956,
          1960,
          1960,
          1960,
          1960,
          1964,
          1964,
          1964,
          1964,
          1968,
          1968,
          1968,
          1968,
          1972,
          1972,
          1972,
          1972,
          1976,
          1976,
          1976,
          1976,
          1980,
          1980,
          1980,
          1980,
          1984,
          1984,
          1984,
          1984,
          1988,
          1988,
          1988,
          1988,
          1992,
          1992,
          1992,
          1992,
          1996,
          1996,
          1996,
          1996,
          2000,
          2000,
          2000,
          2000,
          2004,
          2004,
          2004,
          2004,
          2008,
          2008,
          2008,
          2008,
          2012,
          2012,
          2012,
          2012,
          2016,
          2016,
          2016,
          2016
        ],
        "medal": [
          "Bronze",
          "Gold",
          "No Medal",
          "Silver",
          "Bronze",
          "Gold",
          "No Medal",
          "Silver",
          "Bronze",
          "Gold",
          "No Medal",
          "Silver",
          "Bronze",
          "Gold",
          "No Medal",
          "Silver",
          "Bronze",
          "Gold",
          "No Medal",
          "Silver",
          "Bronze",
          "Gold",
          "No Medal",
          "Silver",
          "Bronze",
          "Gold",
          "No Medal",
          "Silver",
          "Bronze",
          "Gold",
          "No Medal",
          "Silver",
          "Bronze",
          "Gold",
          "No Medal",
          "Silver",
          "Bronze",
          "Gold",
          "No Medal",
          "Silver",
          "Bronze",
          "Gold",
          "No Medal",
          "Silver",
          "Bronze",
          "Gold",
          "No Medal",
          "Silver",
          "Bronze",
          "Gold",
          "No Medal",
          "Silver",
          "Bronze",
          "Gold",
          "No Medal",
          "Silver",
          "Bronze",
          "Gold",
          "No Medal",
          "Silver",
          "Bronze",
          "Gold",
          "No Medal",
          "Silver",
          "Bronze",
          "Gold",
          "No Medal",
          "Silver",
          "Bronze",
          "Gold",
          "No Medal",
          "Silver",
          "Bronze",
          "Gold",
          "No Medal",
          "Silver",
          "Bronze",
          "Gold",
          "No Medal",
          "Silver",
          "Bronze",
          "Gold",
          "No Medal",
          "Silver",
          "Bronze",
          "Gold",
          "No Medal",
          "Silver",
          "Bronze",
          "Gold",
          "No Medal",
          "Silver",
          "Bronze",
          "Gold",
          "No Medal",
          "Silver",
          "Bronze",
          "Gold",
          "No Medal",
          "Silver"
        ],
        "value": [
          22.0,
          23.2,
          25.8,
          22.25,
          25.0,
          25.8,
          26.0,
          22.0,
          19.86,
          22.25,
          21.85,
          21.71,
          21.0,
          21.5,
          20.6,
          22.25,
          22.29,
          20.38,
          21.64,
          20.5,
          20.75,
          20.0,
          21.66,
          22.75,
          22.62,
          22.75,
          22.08,
          22.0,
          21.62,
          21.62,
          22.5,
          22.12,
          22.6,
          22.1,
          22.42,
          23.5,
          22.4,
          23.8,
          22.53,
          22.4,
          22.25,
          22.8,
          22.96,
          22.7,
          23.55,
          23.6,
          23.17,
          24.7,
          23.0,
          23.73,
          22.79,
          25.0,
          23.1,
          23.55,
          23.28,
          24.0,
          23.23,
          20.91,
          22.75,
          22.0,
          22.77,
          21.36,
          22.78,
          22.09,
          22.22,
          20.83,
          22.44,
          21.17,
          23.08,
          24.08,
          22.95,
          21.25,
          22.54,
          22.83,
          23.13,
          22.92,
          22.83,
          23.42,
          23.55,
          25.58,
          22.96,
          25.67,
          23.74,
          23.58,
          24.27,
          23.82,
          23.57,
          23.0,
          23.59,
          25.27,
          23.72,
          25.09,
          24.05,
          24.8,
          23.5,
          25.2,
          23.6,
          24.3,
          24.89,
          24.78
        ]
      },
      "height": {
        "year": [
          1904,
          1904,
          1908,
          1908,
          1908,
          1920,
          1920,
          1920,
          1924,
          1924,
          1924,
          1928,
          1928,
          1932,
          1932,
          1932,
          1932,
          1936,
          1936,
          1936,
          1948,
          1952,
          1952,
          1952,
          1952,
          1956,
          1956,
          1956,
          1956,
          1960,
          1960,
          1960,
          1960,
          1964,
          1964,
          1964,
          1964,
          1968,
          1968,
          1968,
          1968,
          1972,
          1972,
          1972,
          1972,
          1976,
          1976,
          1976,
          1976,
          1980,
          1980,
          1980,
          1980,
          1984,
          1984,
          1984,
          1984,
          1988,
          1988,
          1988,
          1988,
          1992,
          1992,
          1992,
          1992,
          1996,
          1996,
          1996,
          1996,
          2000,
          2000,
          2000,
          2000,
          2004,
          2004,
          2004,
          2004,
          2008,
          2008,
          2008,
          2008,
          2012,
          2012,
          2012,
          2012,
          2016,
          2016,
          2016,
          2016
        ],
        "medal": [
          "Gold",
          "Silver",
          "Bronze",
          "No Medal",
          "Silver",
          "Bronze",
          "Gold",
          "No Medal",
          "Bronze",
          "Gold",
          "No Medal",
          "Gold",
          "No Medal",
          "Bronze",
          "Gold",
          "No Medal",
          "Silver",
          "Gold",
          "No Medal",
          "Silver",
          "No Medal",
          "Bronze",
          "Gold",
          "No Medal",
          "Silver",
          "Bronze",
          "Gold",
          "No Medal",
          "Silver",
          "Bronze",
          "Gold",
          "No Medal",
          "Silver",
          "Bronze",
          "Gold",
          "No Medal",
          "Silver",
          "Bronze",
          "Gold",
          "No Medal",
          "Silver",
          "Bronze",
          "Gold",
          "No Medal",
          "Silver",
          "Bronze",
          "Gold",
          "No Medal",
          "Silver",
          "Bronze",
          "Gold",
          "No Medal",
          "Silver",
          "Bronze",
          "Gold",
          "No Medal",
          "Silver",
          "Bronze",
          "Gold",
          "No Medal",
          "Silver",
          "Bronze",
          "Gold",
          "No Medal",
          "Silver",
          "Bronze",
          "Gold",
          "No Medal",
          "Silver",
          "Bronze",
          "Gold",
          "No Medal",
          "Silver",
          "Bronze",
          "Gold",
          "No Medal",
          "Silver",
          "Bronze",
          "Gold",
          "No Medal",
          "Silver",
          "Bronze",
          "Gold",
          "No Medal",
          "Silver",
          "Bronze",
          "Gold",
          "No Medal",
          "Silver"
        ],
        "value": [
          188.0,
          160.0,
          180.0,
          165.0,
          178.0,
          170.0,
          167.8,
          172.33,
          181.5,
          176.0,
          177.26,
          172.5,
          171.29,
          171.33,
          171.0,
          170.28,
          171.2,
          166.5,
          172.65,
          176.5,
          172.36,
          179.33,
          172.67,
          173.05,
          184.0,
          175.14,
          175.4,
          174.38,
          168.0,
          174.53,
          172.4,
          170.8,
          170.4,
          171.9,
          170.0,
          170.99,
          172.4,
          173.14,
          175.0,
          170.31,
          171.36,
          171.36,
          174.36,
          170.26,
          173.0,
          173.59,
          176.45,
          171.96,
          175.5,
          172.36,
          174.36,
          170.96,
          172.0,
          176.47,
          177.58,
          171.87,
          174.75,
          176.35,
          175.83,
          171.82,
          176.58,
          175.48,
          172.18,
          174.04,
          173.58,
          173.61,
          176.92,
          174.02,
          175.08,
          174.46,
          176.5,
          173.98,
          174.92,
          175.95,
          173.82,
          174.02,
          174.73,
          177.82,
          174.82,
          174.51,
          175.9,
          178.1,
          178.7,
          175.43,
          174.8,
          177.0,
          176.4,
          174.88,
          178.89
        ]
      },
      "weight": {
        "year": [
          1904,
          1904,
          1904,
          1904,
          1908,
          1920,
          1920,
          1924,
          1924,
          1924,
          1928,
          1928,
          1928,
          1932,
          1932,
          1932,
          1936,
          1936,
          1936,
          1948,
          1952,
          1952,
          1952,
          1956,
          1956,
          1956,
          1956,
          1960,
          1960,
          1960,
          1960,
          1964,
          1964,
          1964,
          1964,
          1968,
          1968,
          1968,
          1968,
          1972,
          1972,
          1972,
          1972,
          1976,
          1976,
          1976,
          1976,
          1980,
          1980,
          1980,
          1980,
          1984,
          1984,
          1984,
          1984,
          1988,
          1988,
          1988,
          1988,
          1992,
          1992,
          1992,
          1992,
          1996,
          1996,
          1996,
          1996,
          2000,
          2000,
          2000,
          2000,
          2004,
          2004,
          2004,
          2004,
          2008,
          2008,
          2008,
          2008,
          2012,
          2012,
          2012,
          2012,
          2016,
          2016,
          2016,
          2016
        ],
        "medal": [
          "Bronze",
          "Gold",
          "No Medal",
          "Silver",
          "No Medal",
          "Gold",
          "No Medal",
          "Bronze",
          "Gold",
          "No Medal",
          "Gold",
          "No Medal",
          "Silver",
          "Bronze",
          "Gold",
          "No Medal",
          "Gold",
          "No Medal",
          "Silver",
          "No Medal",
          "Bronze",
          "Gold",
          "No Medal",
          "Bronze",
          "Gold",
          "No Medal",
          "Silver",
          "Bronze",
          "Gold",
          "No Medal",
          "Silver",
          "Bronze",
          "Gold",
          "No Medal",
          "Silver",
          "Bronze",
          "Gold",
          "No Medal",
          "Silver",
          "Bronze",
          "Gold",
          "No Medal",
          "Silver",
          "Bronze",
          "Gold",
          "No Medal",
          "Silver",
          "Bronze",
          "Gold",
          "No Medal",
          "Silver",
          "Bronze",
          "Gold",
          "No Medal",
          "Silver",
          "Bronze",
          "Gold",
          "No Medal",
          "Silver",
          "Bronze",
          "Gold",
          "No Medal",
          "Silver",
          "Bronze",
          "Gold",
          "No Medal",
          "Silver",
          "Bronze",
          "Gold",
          "No Medal",
          "Silver",
          "Bronze",
          "Gold",
          "No Medal",
          "Silver",
          "Bronze",
          "Gold",
          "No Medal",
          "Silver",
          "Bronze",
          "Gold",
          "No Medal",
          "Silver",
          "Bronze",
          "Gold",
          "No Medal",
          "Silver"
        ],
        "value": [
          68.5,
          61.71,
          60.0,
          59.57,
          73.0,
          50.5,
          58.0,
          86.0,
          66.67,
          73.11,
          62.0,
          66.43,
          50.0,
          69.5,
          60.75,
          86.0,
          58.75,
          69.29,
          60.0,
          68.41,
          79.33,
          65.17,
          69.53,
          70.75,
          75.0,
          71.48,
          65.0,
          67.53,
          67.4,
          64.43,
          66.2,
          66.8,
          67.6,
          63.58,
          66.8,
          65.45,
          67.36,
          63.09,
          64.82,
          65.55,
          65.73,
          62.62,
          64.55,
          65.82,
          64.45,
          63.34,
          63.1,
          64.59,
          65.27,
          62.9,
          64.73,
          69.63,
          68.17,
          64.92,
          68.17,
          67.29,
          68.5,
          63.98,
          68.25,
          70.17,
          67.82,
          66.03,
          66.92,
          66.48,
          68.83,
          66.72,
          72.33,
          69.33,
          68.83,
          65.56,
          68.25,
          68.16,
          68.73,
          65.7,
          68.0,
          68.95,
          68.95,
          65.88,
          69.18,
          68.89,
          66.43,
          67.69,
          70.55,
          69.3,
          69.4,
          66.77,
          72.56
        ]
      }
    },
    "F": {
      "age": {
        "year": [
          2012,
          2012,
          2012,
          2012,
          2016,
          2016,
          2016,
          2016
        ],
        "medal": [
          "Bronze",
          "Gold",
          "No Medal",
          "Silver",
          "Bronze",
          "Gold",
          "No Medal",
          "Silver"
        ],
        "value": [
          24.0,
          24.0,
          26.88,
          27.33,
          27.67,
          25.67,
          26.88,
          29.0
        ]
      },
      "height": {
        "year": [
          2012,
          2012,
          2012,
          2012,
          2016,
          2016,
          2016,
          2016
        ],
        "medal": [
          "Bronze",
          "Gold",
          "No Medal",
          "Silver",
          "Bronze",
          "Gold",
          "No Medal",
          "Silver"
        ],
        "value": [
          165.17,
          168.0,
          170.27,
          170.67,
          169.5,
          169.0,
          168.08,
          168.33
        ]
      },
      "weight": {
        "year": [
          2012,
          2012,
          2012,
          2012,
          2016,
          2016,
          2016,
          2016
        ],
        "medal": [
          "Bronze",
          "Gold",
          "No Medal",
          "Silver",
          "Bronze",
          "Gold",
          "No Medal",
          "Silver"
        ],
        "value": [
          59.4,
          62.0,
          62.29,
          62.0,
          61.83,
          62.0,
          62.0,
          62.0
        ]
      }
    }
  }
}